eurlex/__init__.py
tests/__init__.py
tests/test_parsing.py
eurlex-0.1.4.dist-info/METADATA
eurlex-0.1.4.dist-info/WHEEL
eurlex-0.1.4.dist-info/top_level.txt
eurlex-0.1.4.dist-info/RECORD
