Metadata-Version: 2.1
Name: eurlex
Version: 0.1.4
Summary: An EUR-Lex parser for Python.
Home-page: https://github.com/kevin91nl/eurlex
Author: K.M.J. Jacobs
Author-email: kmj.jacobs@maastrichtuniversity.nl
License: UNKNOWN
Platform: UNKNOWN
Requires-Python: >=3.6
Requires-Dist: argparse (==1.4.0)
Requires-Dist: sparqlwrapper (==1.8.5)
Requires-Dist: pandas (==1.2.4)
Requires-Dist: rdflib (==6.0.2)
Requires-Dist: requests (==2.25.1)
Requires-Dist: bs4 (==0.0.1)
Requires-Dist: beautifulsoup4 (==4.9.3)
